rpcsniffer/Config.py
rpcsniffer/OutputFormatter.py
rpcsniffer/PacketDecoder.py
rpcsniffer/__init__.py
rpcsniffer/__version__.py
rpcsniffer-0.1.1.data/scripts/rpc-sniffer.py
rpcsniffer-0.1.1.dist-info/DESCRIPTION.rst
rpcsniffer-0.1.1.dist-info/METADATA
rpcsniffer-0.1.1.dist-info/RECORD
rpcsniffer-0.1.1.dist-info/WHEEL
rpcsniffer-0.1.1.dist-info/metadata.json
rpcsniffer-0.1.1.dist-info/top_level.txt
