Metadata-Version: 2.0
Name: rpcsniffer
Version: 0.1.1
Summary: Capture and decode (Ethereum) JSON RPC traffic
Home-page: https://github.com/alext234/rpc-sniffer
Author: Alex Tran
Author-email: alex.tran234@gmail.com
License: MIT
Platform: UNKNOWN
Classifier: License :: OSI Approved :: MIT License
Classifier: Programming Language :: Python
Classifier: Programming Language :: Python :: 3
Classifier: Programming Language :: Python :: 3.6
Classifier: Programming Language :: Python :: Implementation :: CPython
Classifier: Programming Language :: Python :: Implementation :: PyPy
Requires-Python: >=3.0.0
Requires-Dist: scapy-python3
